README.md
requirements.txt
setup.py
microgp/README.md
microgp/__init__.py
microgp/abstract.py
microgp/archive.py
microgp/common_data_structures.py
microgp/constraints.py
microgp/darwin.py
microgp/default_builders.py
microgp/genetic_operators.py
microgp/genoperator.py
microgp/graph.py
microgp/individual.py
microgp/macro.py
microgp/node.py
microgp/operators.py
microgp/population.py
microgp/properties.py
microgp/simple_tree.py
microgp/standard_checkers.py
microgp.egg-info/PKG-INFO
microgp.egg-info/SOURCES.txt
microgp.egg-info/dependency_links.txt
microgp.egg-info/requires.txt
microgp.egg-info/top_level.txt
microgp/fitness/__init__.py
microgp/fitness/aggregate.py
microgp/fitness/base.py
microgp/fitness/chromatic.py
microgp/fitness/evaluator.py
microgp/fitness/fitnesstuple.py
microgp/fitness/fitnesstuplemultiobj.py
microgp/fitness/lexicase.py
microgp/fitness/lexicographic.py
microgp/fitness/simple.py
microgp/parameter/__init__.py
microgp/parameter/abstract.py
microgp/parameter/bitstring.py
microgp/parameter/categorical.py
microgp/parameter/helpers.py
microgp/parameter/information.py
microgp/parameter/integer.py
microgp/parameter/reference.py
microgp/utils/__init__.py
microgp/utils/cpu_time.py
microgp/utils/logging.py
microgp/utils/plural.py
microgp/utils/random.py