Metadata-Version: 2.1
Name: microgp
Version: 4!1.0a0.dev26
Summary: A multi-purpose extensible self-adaptive evolutionary algorithm
Home-page: https://squillero.github.io/microgp4/
Author: Giovanni Squillero
Author-email: squillero@polito.it
License: Apache-2.0
Project-URL: Bug Tracker, https://github.com/squillero/microgp4/issues
Project-URL: Documentation, https://microgp4.readthedocs.io/en/pre-alpha/
Project-URL: Source Code, https://github.com/squillero/microgp4/tree/pre-alpha
Keywords: optimization evolutionary-algorithm computational-intelligence
Platform: UNKNOWN
Classifier: Programming Language :: Python :: 3
Classifier: Operating System :: OS Independent
Classifier: Development Status :: 2 - Pre-Alpha
Classifier: Intended Audience :: Science/Research
Classifier: Topic :: Scientific/Engineering :: Artificial Intelligence
Classifier: License :: OSI Approved :: Apache Software License
